edit_distance_correction/__init__.py
edit_distance_correction/correction.csv
edit_distance_correction/correction.py
edit_distance_correction/heteronym.txt
edit_distance_correction/same_stroke.txt
edit_distance_correction/target_words
edit_distance_correction/test.py
edit_distance_correction/test_file
edit_distance_correction/utils.py
edit_distance_correction/valid_pinyin
edit_distance_correction-1.1.8.dist-info/METADATA
edit_distance_correction-1.1.8.dist-info/WHEEL
edit_distance_correction-1.1.8.dist-info/top_level.txt
edit_distance_correction-1.1.8.dist-info/RECORD
